patternq/__init__.py
patternq-0.0.0.dist-info/LICENSE
patternq-0.0.0.dist-info/METADATA
patternq-0.0.0.dist-info/WHEEL
patternq-0.0.0.dist-info/top_level.txt
patternq-0.0.0.dist-info/RECORD
