Metadata-Version: 2.1
Name: patternq
Version: 0.0.0
Summary: A tool for quantifying subcellular fluorescence pattern changes
Home-page: https://patternq.org
Author: Ira Novianti
License: BSD-2-Clause
Classifier: Programming Language :: Python :: 3
Classifier: License :: OSI Approved :: BSD License
Classifier: Operating System :: OS Independent
Classifier: Development Status :: 1 - Planning
Requires-Python: >=3.6
License-File: LICENSE
